{"game":"eu4","name":"USA","mods":[{"displayName":"Development Expanded","enabled":true,"position":0,"steamId":"1880075247"},{"displayName":"Buy a Province","enabled":true,"position":1,"steamId":"686284192"},{"displayName":"More Diplomats","enabled":true,"position":2,"steamId":"1736651173"},{"displayName":"Uber Custom Nations","enabled":true,"position":3,"steamId":"947749925"},{"displayName":"Higher Diplomatic Relations Limit Remastered","enabled":true,"position":4,"steamId":"1546826435"},{"displayName":"Governments Expanded","enabled":true,"position":5,"steamId":"1596815683"},{"displayName":"Best Unit Type+","enabled":true,"position":6,"steamId":"1994447693"},{"displayName":"Cmushi's Simpler Terms Mod [Updated]","enabled":true,"position":7,"steamId":"1999969598"},{"displayName":"Banners 4.0","enabled":true,"position":8,"steamId":"2129713984"},{"displayName":"Flavour and Events Expanded","enabled":true,"position":9,"steamId":"2185445645"},{"displayName":"The Great Exhibition","enabled":true,"position":10,"steamId":"2016264376"},{"displayName":"Ze Great Kaiser's Cheat Menu (Reupload)","enabled":true,"position":11,"steamId":"2136257369"},{"displayName":"Buy Building Slots","enabled":true,"position":12,"steamId":"716527938"},{"displayName":"Idea Groups Expanded 1.33","enabled":true,"position":13,"steamId":"2128766791"},{"displayName":"Subjects Expanded","enabled":true,"position":14,"steamId":"1834079712"},{"displayName":"Advisors Expanded 1.33","enabled":true,"position":15,"steamId":"2141678271"},{"displayName":"Flavor Universalis","enabled":true,"position":16,"steamId":"2372292648"},{"displayName":"Ad Lucem","enabled":true,"position":17,"steamId":"1469605293"},{"displayName":"Better Terrain Pictures","enabled":true,"position":18,"steamId":"1417122689"},{"displayName":"Bigger Production UI V1.37","enabled":true,"position":19,"steamId":"782012869"},{"displayName":"UI a la Artemis","enabled":true,"position":21,"steamId":"2291982168"},{"displayName":"[1.33] More Policy Slots","enabled":true,"position":22,"steamId":"2553303821"},{"displayName":"Peace Treaties Expanded","enabled":true,"position":23,"steamId":"2615504872"},{"displayName":"IDEA SLOTS+","enabled":true,"position":24,"steamId":"2595181784"},{"displayName":"Great Monuments Expanded","enabled":true,"position":25,"steamId":"2469419235"},{"displayName":"Defender of faith for all religions","enabled":true,"position":26,"steamId":"2554763672"},{"displayName":"Trade Goods Expanded","enabled":true,"position":27,"steamId":"1770950522"},{"displayName":"Land of the Free (USA Overhaul Mod)","enabled":true,"position":28,"steamId":"2677462796"},{"displayName":"49th Parallel","enabled":true,"position":29,"steamId":"2617232208"},{"displayName":"Advisor Types Expanded","enabled":true,"position":30,"steamId":"2737385499"}]}